{
  "quote": {
    "text": "helloooo",
    "author": "ooo"
  },
  "todos": [
    {
      "id": 1,
      "text": "Review today's notes",
      "done": true
    },
    {
      "id": 200,
      "text": "clean room",
      "done": true
    }
  ],
  "events": [
    {
      "id": 1,
      "time": "09:00",
      "title": "Morning standup",
      "description": ""
    },
    {
      "id": 2,
      "time": "14:00",
      "title": "Deep work block",
      "description": "No interruptions"
    }
  ],
  "background": "/images/background.jpg",
  "updated_at": "2026-05-18T21:06:59.395Z",
  "interval": 86400,
  "sshenabled": false,
  "keepalive": -1,
  "battery": 32,
  "wifi_up": true
}